MANIFEST.in
readme.rst
setup.cfg
setup.py
ape/__init__.py
ape/conf.py
ape/log_setter.py
ape/main.py
ape/components/__init__.py
ape/components/component.py
ape/components/index.py
ape/components/test_components.py
ape/documentation/__init__.py
ape/documentation/developer/__init__.py
ape/documentation/developer/explorations/__init__.py
ape/documentation/developer/explorations/explore_configparse/__init__.py
ape/documentation/developer/explorations/explore_configparse/explore_configparse.py
ape/documentation/developer/explorations/explore_configparse/index.py
ape/documentation/developer/explorations/explore_dateutil/__init__.py
ape/documentation/developer/explorations/explore_dateutil/dateutil_api.py
ape/documentation/developer/explorations/explore_dateutil/explore_dateutil.py
ape/documentation/developer/explorations/explore_dateutil/index.py
ape/documentation/developer/explorations/explore_exceptions/__init__.py
ape/documentation/developer/explorations/explore_exceptions/exploring_exceptions.py
ape/documentation/developer/explorations/explore_exceptions/index.py
ape/documentation/developer/explorations/explore_files/__init__.py
ape/documentation/developer/explorations/explore_files/exploring_files.py
ape/documentation/developer/explorations/explore_files/index.py
ape/documentation/developer/explorations/explore_graphs/__init__.py
ape/documentation/developer/explorations/explore_graphs/example_cases.py
ape/documentation/developer/explorations/explore_graphs/explore_code2flow.py
ape/documentation/developer/explorations/explore_graphs/explore_pycallgraph.py
ape/documentation/developer/explorations/explore_graphs/explore_pyreverse.py
ape/documentation/developer/explorations/explore_graphs/index.py
ape/documentation/developer/explorations/explore_importlib/__init__.py
ape/documentation/developer/explorations/explore_importlib/exploring_external_imports.py
ape/documentation/developer/explorations/explore_importlib/index.py
theape.egg-info/PKG-INFO
theape.egg-info/SOURCES.txt
theape.egg-info/dependency_links.txt
theape.egg-info/entry_points.txt
theape.egg-info/requires.txt
theape.egg-info/top_level.txt