Metadata-Version: 1.0
Name: theape
Version: 2014.11.10
Summary: The All-Purpose Experimenter.
Home-page: UNKNOWN
Author: russell
Author-email: necromuralist@gmail.com
License: UNKNOWN
Platform: linux
